quask/__init__.py
quask/__main__.py
quask/datasets.py
quask/kernels.py
quask/metrics.py
quask/template_pennylane.py
quask/resources/__init__.py
quask/techniques/__init__.py
quask/techniques/combinatorial_kernel.py
quask/techniques/combinatorial_kernel_genetic.py
quask/techniques/combinatorial_kernel_greedy.py
quask/techniques/combinatorial_kernel_simanneal.py
quask/techniques/random_kernel.py
quask/techniques/scrambled_kernel.py
quask/techniques/trainable_kernel.py
quask-1.0.2.dist-info/LICENSE
quask-1.0.2.dist-info/METADATA
quask-1.0.2.dist-info/WHEEL
quask-1.0.2.dist-info/top_level.txt
quask-1.0.2.dist-info/RECORD
