Metadata-Version: 2.1
Name: quask
Version: 1.0.2
Summary: A software framework to speed up the research in quantum machine learning
Home-page: https://github.com/CERN-IT-INNOVATION/QuASK
Author: Massimiliano Incudini <massimiliano.incudini@univr.it>, Francesco Di Marcantonio <francesco.di.marcantonio@cern.ch>, Michele Grossi <michele.grossi@cern.ch>
Author-email: Massimiliano Incudini <massimiliano.incudini@univr.it>, Francesco Di Marcantonio <francesco.di.marcantonio@cern.ch>, Michele Grossi <michele.grossi@cern.ch>
License: Apache License Version 2.0
Project-URL: Homepage, https://github.com/CERN-IT-INNOVATION/QuASK
Project-URL: Bug Tracker, https://github.com/CERN-IT-INNOVATION/QuASK/issues
Classifier: License :: OSI Approved :: Apache Software License
Classifier: Operating System :: Unix
Classifier: Topic :: Scientific/Engineering :: Physics
Classifier: Programming Language :: Python :: 3.9
Requires-Python: >=3.7.0
License-File: LICENSE
Requires-Dist: matplotlib
Requires-Dist: numpy
Requires-Dist: scipy
Requires-Dist: click
Requires-Dist: scikit-learn
Requires-Dist: imbalanced-learn
Requires-Dist: prince
Requires-Dist: openml
Requires-Dist: jax
Requires-Dist: jaxlib
Requires-Dist: PennyLane
Requires-Dist: PennyLane-qiskit
Requires-Dist: simanneal
Requires-Dist: optax
Provides-Extra: demo
Requires-Dist: jupyter ; extra == 'demo'
Provides-Extra: docs
Requires-Dist: sphinx (>=4.5.0) ; extra == 'docs'
Requires-Dist: sphinx-rtd-theme (>=1.0.0) ; extra == 'docs'
Requires-Dist: sphinxcontrib-napoleon (>=0.7) ; extra == 'docs'
Requires-Dist: sphinx-autoapi (>=2.0.1) ; extra == 'docs'
